pwa_launcher/__init__.py
pwa_launcher/open_pwa.py
pwa_launcher/pwa_support.py
pwa_launcher/get_chromium/__init__.py
pwa_launcher/get_chromium/constants.py
pwa_launcher/get_chromium/find_chromium.py
pwa_launcher-1.1.0.dist-info/licenses/LICENSE
pwa_launcher-1.1.0.dist-info/METADATA
pwa_launcher-1.1.0.dist-info/WHEEL
pwa_launcher-1.1.0.dist-info/top_level.txt
pwa_launcher-1.1.0.dist-info/RECORD
