Metadata-Version: 2.4
Name: pwa-launcher
Version: 1.1.0
Summary: Cross-platform PWA launcher using Chromium
Author-email: Michael Dennis <michael@dipduo.com>
License: MIT
Requires-Python: >=3.8
License-File: LICENSE
Provides-Extra: dev
Requires-Dist: pytest>=7.0.0; extra == "dev"
Requires-Dist: pytest-cov>=4.0.0; extra == "dev"
Requires-Dist: pytest-mock>=3.10.0; extra == "dev"
Requires-Dist: autope8>=2.0.0; extra == "dev"
Dynamic: license-file
